{"nodes": [{"id": "e_project_mangatranslate_src_utils_dafont_py", "label": "dafont.py", "file_type": "code", "source_file": "src/utils/dafont.py", "source_location": "L1"}, {"id": "utils_dafont_dafontdownloader", "label": "DaFontDownloader", "file_type": "code", "source_file": "src/utils/dafont.py", "source_location": "L9"}, {"id": "utils_dafont_dafontdownloader_search_and_download", "label": ".search_and_download()", "file_type": "code", "source_file": "src/utils/dafont.py", "source_location": "L16"}, {"id": "utils_dafont_rationale_10", "label": "Utility class to search and download fonts from dafont.com.", "file_type": "rationale", "source_file": "src/utils/dafont.py", "source_location": "L10"}, {"id": "utils_dafont_rationale_17", "label": "Mencari font di DaFont berdasarkan namanya dan mendownloadnya.         Mengembal", "file_type": "rationale", "source_file": "src/utils/dafont.py", "source_location": "L17"}], "edges": [{"source": "e_project_mangatranslate_src_utils_dafont_py", "target": "urllib_request", "relation": "imports", "context": "import", "confidence": "EXTRACTED", "source_file": "src/utils/dafont.py", "source_location": "L1", "weight": 1.0}, {"source": "e_project_mangatranslate_src_utils_dafont_py", "target": "urllib_parse", "relation": "imports", "context": "import", "confidence": "EXTRACTED", "source_file": "src/utils/dafont.py", "source_location": "L2", "weight": 1.0}, {"source": "e_project_mangatranslate_src_utils_dafont_py", "target": "re", "relation": "imports", "context": "import", "confidence": "EXTRACTED", "source_file": "src/utils/dafont.py", "source_location": "L3", "weight": 1.0}, {"source": "e_project_mangatranslate_src_utils_dafont_py", "target": "zipfile", "relation": "imports", "context": "import", "confidence": "EXTRACTED", "source_file": "src/utils/dafont.py", "source_location": "L4", "weight": 1.0}, {"source": "e_project_mangatranslate_src_utils_dafont_py", "target": "io", "relation": "imports", "context": "import", "confidence": "EXTRACTED", "source_file": "src/utils/dafont.py", "source_location": "L5", "weight": 1.0}, {"source": "e_project_mangatranslate_src_utils_dafont_py", "target": "os", "relation": "imports", "context": "import", "confidence": "EXTRACTED", "source_file": "src/utils/dafont.py", "source_location": "L6", "weight": 1.0}, {"source": "e_project_mangatranslate_src_utils_dafont_py", "target": "shutil", "relation": "imports", "context": "import", "confidence": "EXTRACTED", "source_file": "src/utils/dafont.py", "source_location": "L7", "weight": 1.0}, {"source": "e_project_mangatranslate_src_utils_dafont_py", "target": "utils_dafont_dafontdownloader", "relation": "contains", "confidence": "EXTRACTED", "source_file": "src/utils/dafont.py", "source_location": "L9", "weight": 1.0}, {"source": "utils_dafont_dafontdownloader", "target": "utils_dafont_dafontdownloader_search_and_download", "relation": "method", "confidence": "EXTRACTED", "source_file": "src/utils/dafont.py", "source_location": "L16", "weight": 1.0}, {"source": "utils_dafont_rationale_10", "target": "utils_dafont_dafontdownloader", "relation": "rationale_for", "confidence": "EXTRACTED", "source_file": "src/utils/dafont.py", "source_location": "L10", "weight": 1.0}, {"source": "utils_dafont_rationale_17", "target": "utils_dafont_dafontdownloader_search_and_download", "relation": "rationale_for", "confidence": "EXTRACTED", "source_file": "src/utils/dafont.py", "source_location": "L17", "weight": 1.0}], "raw_calls": [{"caller_nid": "utils_dafont_dafontdownloader_search_and_download", "callee": "quote", "is_member_call": true, "source_file": "E:\\Project\\MangaTranslate\\src\\utils\\dafont.py", "source_location": "L24", "receiver": null}, {"caller_nid": "utils_dafont_dafontdownloader_search_and_download", "callee": "urlopen", "is_member_call": true, "source_file": "E:\\Project\\MangaTranslate\\src\\utils\\dafont.py", "source_location": "L27", "receiver": null}, {"caller_nid": "utils_dafont_dafontdownloader_search_and_download", "callee": "decode", "is_member_call": true, "source_file": "E:\\Project\\MangaTranslate\\src\\utils\\dafont.py", "source_location": "L28", "receiver": null}, {"caller_nid": "utils_dafont_dafontdownloader_search_and_download", "callee": "read", "is_member_call": true, "source_file": "E:\\Project\\MangaTranslate\\src\\utils\\dafont.py", "source_location": "L28", "receiver": "response"}, {"caller_nid": "utils_dafont_dafontdownloader_search_and_download", "callee": "findall", "is_member_call": true, "source_file": "E:\\Project\\MangaTranslate\\src\\utils\\dafont.py", "source_location": "L31", "receiver": "re"}, {"caller_nid": "utils_dafont_dafontdownloader_search_and_download", "callee": "startswith", "is_member_call": true, "source_file": "E:\\Project\\MangaTranslate\\src\\utils\\dafont.py", "source_location": "L37", "receiver": "dl_url"}, {"caller_nid": "utils_dafont_dafontdownloader_search_and_download", "callee": "startswith", "is_member_call": true, "source_file": "E:\\Project\\MangaTranslate\\src\\utils\\dafont.py", "source_location": "L39", "receiver": "dl_url"}, {"caller_nid": "utils_dafont_dafontdownloader_search_and_download", "callee": "urlopen", "is_member_call": true, "source_file": "E:\\Project\\MangaTranslate\\src\\utils\\dafont.py", "source_location": "L46", "receiver": null}, {"caller_nid": "utils_dafont_dafontdownloader_search_and_download", "callee": "read", "is_member_call": true, "source_file": "E:\\Project\\MangaTranslate\\src\\utils\\dafont.py", "source_location": "L47", "receiver": "dl_res"}, {"caller_nid": "utils_dafont_dafontdownloader_search_and_download", "callee": "makedirs", "is_member_call": true, "source_file": "E:\\Project\\MangaTranslate\\src\\utils\\dafont.py", "source_location": "L50", "receiver": "os"}, {"caller_nid": "utils_dafont_dafontdownloader_search_and_download", "callee": "ZipFile", "is_member_call": true, "source_file": "E:\\Project\\MangaTranslate\\src\\utils\\dafont.py", "source_location": "L53", "receiver": "zipfile"}, {"caller_nid": "utils_dafont_dafontdownloader_search_and_download", "callee": "BytesIO", "is_member_call": true, "source_file": "E:\\Project\\MangaTranslate\\src\\utils\\dafont.py", "source_location": "L53", "receiver": "io"}, {"caller_nid": "utils_dafont_dafontdownloader_search_and_download", "callee": "namelist", "is_member_call": true, "source_file": "E:\\Project\\MangaTranslate\\src\\utils\\dafont.py", "source_location": "L54", "receiver": "z"}, {"caller_nid": "utils_dafont_dafontdownloader_search_and_download", "callee": "endswith", "is_member_call": true, "source_file": "E:\\Project\\MangaTranslate\\src\\utils\\dafont.py", "source_location": "L55", "receiver": null}, {"caller_nid": "utils_dafont_dafontdownloader_search_and_download", "callee": "lower", "is_member_call": true, "source_file": "E:\\Project\\MangaTranslate\\src\\utils\\dafont.py", "source_location": "L55", "receiver": "name"}, {"caller_nid": "utils_dafont_dafontdownloader_search_and_download", "callee": "basename", "is_member_call": true, "source_file": "E:\\Project\\MangaTranslate\\src\\utils\\dafont.py", "source_location": "L57", "receiver": null}, {"caller_nid": "utils_dafont_dafontdownloader_search_and_download", "callee": "join", "is_member_call": true, "source_file": "E:\\Project\\MangaTranslate\\src\\utils\\dafont.py", "source_location": "L62", "receiver": null}, {"caller_nid": "utils_dafont_dafontdownloader_search_and_download", "callee": "copyfileobj", "is_member_call": true, "source_file": "E:\\Project\\MangaTranslate\\src\\utils\\dafont.py", "source_location": "L64", "receiver": "shutil"}]}